Metadata-Version: 2.1
Name: yorumsepeti
Version: 0.0.4
Summary: A package for fetching restaurant reviews from Yemeksepeti.com.
Home-page: https://github.com/dgknrsln/yorumsepeti
Author: Doğukan Arslan
Author-email: dogukan997@hotmail.com
License: UNKNOWN
Project-URL: Bug Tracker, https://github.com/dgknrsln/yorumsepeti/issues
Platform: UNKNOWN
Classifier: Programming Language :: Python :: 3
Classifier: License :: OSI Approved :: MIT License
Classifier: Operating System :: OS Independent
Requires-Python: >=3.6
